lego_wireless/__init__.py
lego_wireless/__main__.py
lego_wireless/constants.py
lego_wireless/enums.py
lego_wireless/hub.py
lego_wireless/hub_io.py
lego_wireless/manager.py
lego_wireless/messages.py
lego_wireless/signals.py
lego_wireless-0.2.1.dist-info/WHEEL
lego_wireless-0.2.1.dist-info/METADATA
lego_wireless-0.2.1.dist-info/RECORD
